MANIFEST.in
README.md
setup.py
version.txt
leveldbs/__init__.py
leveldbs/client.py
leveldbs/zmq_client.py
leveldbs.egg-info/PKG-INFO
leveldbs.egg-info/SOURCES.txt
leveldbs.egg-info/dependency_links.txt
leveldbs.egg-info/requires.txt
leveldbs.egg-info/top_level.txt