Metadata-Version: 1.0
Name: leveldbs
Version: 0.1.26
Summary: time and path tool
Home-page: https://github.com/infinityfuture/leveldb-server
Author: infinityfuture
Author-email: infinityfuture@foxmail.com
License: MIT Licence
Keywords: pip,leveldb
Platform: any
